MANIFEST.in
README
requirements.txt
setup.py
ajenti.plugin.iptables.egg-info/PKG-INFO
ajenti.plugin.iptables.egg-info/SOURCES.txt
ajenti.plugin.iptables.egg-info/dependency_links.txt
ajenti.plugin.iptables.egg-info/top_level.txt
ajenti_plugin_iptables/.gitignore
ajenti_plugin_iptables/README.md
ajenti_plugin_iptables/__init__.py
ajenti_plugin_iptables/main.py
ajenti_plugin_iptables/plugin.yml
ajenti_plugin_iptables/requirements.txt
ajenti_plugin_iptables/views.py
ajenti_plugin_iptables/locale/af/LC_MESSAGES/app.js
ajenti_plugin_iptables/locale/af/LC_MESSAGES/app.po
ajenti_plugin_iptables/locale/ar/LC_MESSAGES/app.js
ajenti_plugin_iptables/locale/ar/LC_MESSAGES/app.po
ajenti_plugin_iptables/locale/be/LC_MESSAGES/app.js
ajenti_plugin_iptables/locale/be/LC_MESSAGES/app.po
ajenti_plugin_iptables/locale/bg/LC_MESSAGES/app.js
ajenti_plugin_iptables/locale/bg/LC_MESSAGES/app.po
ajenti_plugin_iptables/locale/bn/LC_MESSAGES/app.js
ajenti_plugin_iptables/locale/bn/LC_MESSAGES/app.po
ajenti_plugin_iptables/locale/bs/LC_MESSAGES/app.js
ajenti_plugin_iptables/locale/bs/LC_MESSAGES/app.po
ajenti_plugin_iptables/locale/ca/LC_MESSAGES/app.js
ajenti_plugin_iptables/locale/ca/LC_MESSAGES/app.po
ajenti_plugin_iptables/locale/cs/LC_MESSAGES/app.js
ajenti_plugin_iptables/locale/cs/LC_MESSAGES/app.po
ajenti_plugin_iptables/locale/da/LC_MESSAGES/app.js
ajenti_plugin_iptables/locale/da/LC_MESSAGES/app.po
ajenti_plugin_iptables/locale/de/LC_MESSAGES/app.js
ajenti_plugin_iptables/locale/de/LC_MESSAGES/app.po
ajenti_plugin_iptables/locale/el/LC_MESSAGES/app.js
ajenti_plugin_iptables/locale/el/LC_MESSAGES/app.po
ajenti_plugin_iptables/locale/en/LC_MESSAGES/app.po
ajenti_plugin_iptables/locale/eo/LC_MESSAGES/app.js
ajenti_plugin_iptables/locale/eo/LC_MESSAGES/app.po
ajenti_plugin_iptables/locale/es-ES/LC_MESSAGES/app.js
ajenti_plugin_iptables/locale/es-ES/LC_MESSAGES/app.po
ajenti_plugin_iptables/locale/et/LC_MESSAGES/app.js
ajenti_plugin_iptables/locale/et/LC_MESSAGES/app.po
ajenti_plugin_iptables/locale/fa/LC_MESSAGES/app.js
ajenti_plugin_iptables/locale/fa/LC_MESSAGES/app.po
ajenti_plugin_iptables/locale/fi/LC_MESSAGES/app.js
